announce/__init__.py
announce/packet.py
socket.io_announce-0.0.5.dist-info/DESCRIPTION.rst
socket.io_announce-0.0.5.dist-info/METADATA
socket.io_announce-0.0.5.dist-info/pydist.json
socket.io_announce-0.0.5.dist-info/RECORD
socket.io_announce-0.0.5.dist-info/top_level.txt
socket.io_announce-0.0.5.dist-info/WHEEL
