Metadata-Version: 2.0
Name: socket.io-announce
Version: 0.0.5
Summary: Socket.io multi-process announcement channel ported to Python
Home-page: https://github.com/GetBlimp/socket.io-announce
Author: Giovanni Collazo
Author-email: hello@gcollazo.com
License: MIT
Keywords: websockets nodejs socket.io socketio
Platform: UNKNOWN
Classifier: Development Status :: 3 - Alpha
Classifier: License :: OSI Approved :: MIT License
Classifier: Programming Language :: Python
Classifier: Programming Language :: Python :: 2.6
Classifier: Programming Language :: Python :: 2.7
Classifier: Programming Language :: Python :: 3.2
Classifier: Programming Language :: Python :: 3.3
Classifier: Topic :: Utilities
Requires-Dist: redis (>=2.9.1)
